create_case_folder/__init__.py
create_case_folder/create_case_folder.py
create_case_folder-0.0.9.dist-info/METADATA
create_case_folder-0.0.9.dist-info/WHEEL
create_case_folder-0.0.9.dist-info/entry_points.txt
create_case_folder-0.0.9.dist-info/top_level.txt
create_case_folder-0.0.9.dist-info/RECORD
