Metadata-Version: 2.1
Name: create-case-folder
Version: 0.0.9
Summary: Create case folder
Home-page: https://github.com/jaytrairat/python-create-case-folder
Author: jaytrairat
Author-email: jaytrairat@outlook.com
